dfgenerator/VERSION
dfgenerator/__init__.py
dfgenerator/__main__.py
dfgenerator/adapters/__init__.py
dfgenerator/adapters/base.py
dfgenerator/adapters/json_schema_adapter.py
dfgenerator/adapters/spark_adapter.py
dfgenerator/adapters/yaml_adapter.py
dfgenerator/cli.py
dfgenerator/core/__init__.py
dfgenerator/core/builders.py
dfgenerator/core/constants.py
dfgenerator/core/factories.py
dfgenerator/core/keys.py
dfgenerator/core/models.py
dfgenerator/core/types.py
dfgenerator/inference/__init__.py
dfgenerator/inference/dataframe_inference.py
dfgenerator/loaders/__init__.py
dfgenerator/loaders/json_schema_loader.py
dfgenerator/loaders/spark_loader.py
dfgenerator/loaders/yaml_loader.py
dfgenerator/presets/__init__.py
dfgenerator/presets/dataset_presets.py
dfgenerator-0.1.1.dist-info/LICENSE
dfgenerator-0.1.1.dist-info/METADATA
dfgenerator-0.1.1.dist-info/WHEEL
dfgenerator-0.1.1.dist-info/entry_points.txt
dfgenerator-0.1.1.dist-info/RECORD
