Metadata-Version: 2.1
Name: dfgenerator
Version: 0.1.1
Summary: Deterministic test DataFrame builder with optional PySpark export
Author: cdahirel
Requires-Python: >=3.10,<4.0
Classifier: Programming Language :: Python :: 3
Classifier: Programming Language :: Python :: 3.10
Classifier: Programming Language :: Python :: 3.11
Classifier: Programming Language :: Python :: 3.12
Requires-Dist: click (>=8.1.7,<9.0.0)
Requires-Dist: faker (>=24.9.0,<25.0.0)
Requires-Dist: pandas (>=2.2.3,<3.0.0)
Requires-Dist: pyyaml (>=6.0.1,<7.0.0)
